<annotation verified="no">
  <folder>maragatham</folder>
  <filename>Database Knee Xrays-Triathlon (Stryker)jpg-im37jpgim355</filename>
  <path>C:\Users\maragathamani\Desktop\Xray Implant files\maragatham\Database Knee Xrays-Triathlon (Stryker)jpg-im37jpgim355.jpg</path>
  <source>
    <database>Unknown</database>
  </source>
  <size>
    <width>720</width>
    <height>1792</height>
    <depth>1</depth>
  </size>
  <segmented>0</segmented>
  <object>
    <name>Knee-Triathlon-Stryker</name>
    <pose>Unspecified</pose>
    <truncated>0</truncated>
    <Difficult>0</Difficult>
    <bndbox>
      <xmin>68</xmin>
      <ymin>650</ymin>
      <xmax>449</xmax>
      <ymax>1185</ymax>
    </bndbox>
  </object>
  <object>
    <name>Knee-Triathlon-Stryker</name>
    <pose>Unspecified</pose>
    <truncated>0</truncated>
    <Difficult>0</Difficult>
    <bndbox>
      <xmin>464</xmin>
      <ymin>1301</ymin>
      <xmax>612</xmax>
      <ymax>1566</ymax>
    </bndbox>
  </object>
</annotation>
