<annotation verified="no">
  <folder>bmw new</folder>
  <filename>images (29)</filename>
  <path>C:\Users\mohanraj\Desktop\images\bmw new\images (29).jpg</path>
  <source>
    <database>Unknown</database>
  </source>
  <size>
    <width>720</width>
    <height>405</height>
    <depth>3</depth>
  </size>
  <segmented>0</segmented>
  <object>
    <name>audi</name>
    <pose>Unspecified</pose>
    <truncated>1</truncated>
    <Difficult>0</Difficult>
    <bndbox>
      <xmin>35</xmin>
      <ymin>121</ymin>
      <xmax>720</xmax>
      <ymax>401</ymax>
    </bndbox>
  </object>
</annotation>
