<annotation>
	<folder>nrmal hand images</folder>
	<filename>image_name793.jpg</filename>
	<path>D:\nrmal hand images\image_name793.jpg</path>
	<source>
		<database>Unknown</database>
	</source>
	<size>
		<width>624</width>
		<height>540</height>
		<depth>3</depth>
	</size>
	<segmented>0</segmented>
	<object>
		<name>non-diseased</name>
		<pose>Unspecified</pose>
		<truncated>0</truncated>
		<difficult>0</difficult>
		<bndbox>
			<xmin>39</xmin>
			<ymin>141</ymin>
			<xmax>447</xmax>
			<ymax>377</ymax>
		</bndbox>
	</object>
</annotation>
