<annotation verified="yes">
  <folder>acura</folder>
  <filename>images74</filename>
  <path>C:\Users\mohanraj\Desktop\acura\images74.jpg</path>
  <source>
    <database>Unknown</database>
  </source>
  <size>
    <width>388</width>
    <height>284</height>
    <depth>3</depth>
  </size>
  <segmented>0</segmented>
  <object>
    <name>acura</name>
    <pose>Unspecified</pose>
    <truncated>0</truncated>
    <Difficult>0</Difficult>
    <bndbox>
      <xmin>50</xmin>
      <ymin>2</ymin>
      <xmax>371</xmax>
      <ymax>216</ymax>
    </bndbox>
  </object>
</annotation>
