<annotation>
	<folder>jpeg images</folder>
	<filename>image_name445.jpg</filename>
	<path>E:\jpeg images\image_name445.jpg</path>
	<source>
		<database>Unknown</database>
	</source>
	<size>
		<width>640</width>
		<height>461</height>
		<depth>3</depth>
	</size>
	<segmented>0</segmented>
	<object>
		<name>hand</name>
		<pose>Unspecified</pose>
		<truncated>0</truncated>
		<difficult>0</difficult>
		<bndbox>
			<xmin>40</xmin>
			<ymin>48</ymin>
			<xmax>455</xmax>
			<ymax>382</ymax>
		</bndbox>
	</object>
</annotation>
