<annotation>
	<folder>train</folder>
	<filename>rgb_1349.png</filename>
	<path>C:\Users\ONEDATA-SUDHARSHAN\Desktop\ML\2set\train\rgb_1349.png</path>
	<source>
		<database>Unknown</database>
	</source>
	<size>
		<width>2481</width>
		<height>3508</height>
		<depth>1</depth>
	</size>
	<segmented>0</segmented>
	<object>
		<name>door</name>
		<pose>Unspecified</pose>
		<truncated>0</truncated>
		<difficult>0</difficult>
		<bndbox>
			<xmin>1419</xmin>
			<ymin>2540</ymin>
			<xmax>1527</xmax>
			<ymax>2653</ymax>
		</bndbox>
	</object>
	<object>
		<name>door</name>
		<pose>Unspecified</pose>
		<truncated>0</truncated>
		<difficult>0</difficult>
		<bndbox>
			<xmin>803</xmin>
			<ymin>1900</ymin>
			<xmax>889</xmax>
			<ymax>2011</ymax>
		</bndbox>
	</object>
	<object>
		<name>door</name>
		<pose>Unspecified</pose>
		<truncated>0</truncated>
		<difficult>0</difficult>
		<bndbox>
			<xmin>913</xmin>
			<ymin>1727</ymin>
			<xmax>1019</xmax>
			<ymax>1819</ymax>
		</bndbox>
	</object>
	<object>
		<name>door</name>
		<pose>Unspecified</pose>
		<truncated>0</truncated>
		<difficult>0</difficult>
		<bndbox>
			<xmin>1191</xmin>
			<ymin>1994</ymin>
			<xmax>1284</xmax>
			<ymax>2071</ymax>
		</bndbox>
	</object>
	<object>
		<name>door</name>
		<pose>Unspecified</pose>
		<truncated>0</truncated>
		<difficult>0</difficult>
		<bndbox>
			<xmin>593</xmin>
			<ymin>1654</ymin>
			<xmax>658</xmax>
			<ymax>1726</ymax>
		</bndbox>
	</object>
	<object>
		<name>window</name>
		<pose>Unspecified</pose>
		<truncated>0</truncated>
		<difficult>0</difficult>
		<bndbox>
			<xmin>462</xmin>
			<ymin>1907</ymin>
			<xmax>505</xmax>
			<ymax>2082</ymax>
		</bndbox>
	</object>
	<object>
		<name>window</name>
		<pose>Unspecified</pose>
		<truncated>0</truncated>
		<difficult>0</difficult>
		<bndbox>
			<xmin>464</xmin>
			<ymin>1575</ymin>
			<xmax>505</xmax>
			<ymax>1648</ymax>
		</bndbox>
	</object>
	<object>
		<name>window</name>
		<pose>Unspecified</pose>
		<truncated>0</truncated>
		<difficult>0</difficult>
		<bndbox>
			<xmin>675</xmin>
			<ymin>1375</ymin>
			<xmax>868</xmax>
			<ymax>1421</ymax>
		</bndbox>
	</object>
	<object>
		<name>window</name>
		<pose>Unspecified</pose>
		<truncated>0</truncated>
		<difficult>0</difficult>
		<bndbox>
			<xmin>701</xmin>
			<ymin>2658</ymin>
			<xmax>807</xmax>
			<ymax>2705</ymax>
		</bndbox>
	</object>
	<object>
		<name>window</name>
		<pose>Unspecified</pose>
		<truncated>0</truncated>
		<difficult>0</difficult>
		<bndbox>
			<xmin>1126</xmin>
			<ymin>2648</ymin>
			<xmax>1385</xmax>
			<ymax>2717</ymax>
		</bndbox>
	</object>
	<object>
		<name>wall</name>
		<pose>Unspecified</pose>
		<truncated>0</truncated>
		<difficult>0</difficult>
		<bndbox>
			<xmin>826</xmin>
			<ymin>2668</ymin>
			<xmax>1113</xmax>
			<ymax>2685</ymax>
		</bndbox>
	</object>
	<object>
		<name>wall</name>
		<pose>Unspecified</pose>
		<truncated>0</truncated>
		<difficult>0</difficult>
		<bndbox>
			<xmin>885</xmin>
			<ymin>1385</ymin>
			<xmax>1017</xmax>
			<ymax>1407</ymax>
		</bndbox>
	</object>
	<object>
		<name>wall</name>
		<pose>Unspecified</pose>
		<truncated>0</truncated>
		<difficult>0</difficult>
		<bndbox>
			<xmin>1030</xmin>
			<ymin>1395</ymin>
			<xmax>1046</xmax>
			<ymax>1803</ymax>
		</bndbox>
	</object>
	<object>
		<name>wall</name>
		<pose>Unspecified</pose>
		<truncated>0</truncated>
		<difficult>0</difficult>
		<bndbox>
			<xmin>1387</xmin>
			<ymin>1495</ymin>
			<xmax>1409</xmax>
			<ymax>1823</ymax>
		</bndbox>
	</object>
	<object>
		<name>wall</name>
		<pose>Unspecified</pose>
		<truncated>0</truncated>
		<difficult>0</difficult>
		<bndbox>
			<xmin>1942</xmin>
			<ymin>1701</ymin>
			<xmax>1968</xmax>
			<ymax>2001</ymax>
		</bndbox>
	</object>
	<object>
		<name>wall</name>
		<pose>Unspecified</pose>
		<truncated>0</truncated>
		<difficult>0</difficult>
		<bndbox>
			<xmin>1738</xmin>
			<ymin>2217</ymin>
			<xmax>1756</xmax>
			<ymax>2442</ymax>
		</bndbox>
	</object>
	<object>
		<name>wall</name>
		<pose>Unspecified</pose>
		<truncated>0</truncated>
		<difficult>0</difficult>
		<bndbox>
			<xmin>1558</xmin>
			<ymin>2440</ymin>
			<xmax>1711</xmax>
			<ymax>2458</ymax>
		</bndbox>
	</object>
	<object>
		<name>window</name>
		<pose>Unspecified</pose>
		<truncated>0</truncated>
		<difficult>0</difficult>
		<bndbox>
			<xmin>1475</xmin>
			<ymin>1962</ymin>
			<xmax>1666</xmax>
			<ymax>2026</ymax>
		</bndbox>
	</object>
	<object>
		<name>window</name>
		<pose>Unspecified</pose>
		<truncated>0</truncated>
		<difficult>0</difficult>
		<bndbox>
			<xmin>1370</xmin>
			<ymin>1856</ymin>
			<xmax>1430</xmax>
			<ymax>1954</ymax>
		</bndbox>
	</object>
</annotation>
