<annotation>
	<folder>Train1</folder>
	<filename>rgb_4364.png</filename>
	<path>C:\Users\ArunOnedata\Desktop\windows_v1.8.0\Train1\rgb_4364.png</path>
	<source>
		<database>Unknown</database>
	</source>
	<size>
		<width>1275</width>
		<height>1650</height>
		<depth>1</depth>
	</size>
	<segmented>0</segmented>
	<object>
		<name>window</name>
		<pose>Unspecified</pose>
		<truncated>0</truncated>
		<difficult>0</difficult>
		<bndbox>
			<xmin>180</xmin>
			<ymin>265</ymin>
			<xmax>405</xmax>
			<ymax>309</ymax>
		</bndbox>
	</object>
	<object>
		<name>window</name>
		<pose>Unspecified</pose>
		<truncated>0</truncated>
		<difficult>0</difficult>
		<bndbox>
			<xmin>405</xmin>
			<ymin>269</ymin>
			<xmax>615</xmax>
			<ymax>304</ymax>
		</bndbox>
	</object>
	<object>
		<name>window</name>
		<pose>Unspecified</pose>
		<truncated>0</truncated>
		<difficult>0</difficult>
		<bndbox>
			<xmin>641</xmin>
			<ymin>267</ymin>
			<xmax>751</xmax>
			<ymax>309</ymax>
		</bndbox>
	</object>
	<object>
		<name>window</name>
		<pose>Unspecified</pose>
		<truncated>0</truncated>
		<difficult>0</difficult>
		<bndbox>
			<xmin>846</xmin>
			<ymin>476</ymin>
			<xmax>895</xmax>
			<ymax>565</ymax>
		</bndbox>
	</object>
	<object>
		<name>window</name>
		<pose>Unspecified</pose>
		<truncated>0</truncated>
		<difficult>0</difficult>
		<bndbox>
			<xmin>967</xmin>
			<ymin>1419</ymin>
			<xmax>1081</xmax>
			<ymax>1456</ymax>
		</bndbox>
	</object>
	<object>
		<name>wall</name>
		<pose>Unspecified</pose>
		<truncated>0</truncated>
		<difficult>0</difficult>
		<bndbox>
			<xmin>398</xmin>
			<ymin>681</ymin>
			<xmax>685</xmax>
			<ymax>700</ymax>
		</bndbox>
	</object>
	<object>
		<name>wall</name>
		<pose>Unspecified</pose>
		<truncated>0</truncated>
		<difficult>0</difficult>
		<bndbox>
			<xmin>660</xmin>
			<ymin>678</ymin>
			<xmax>686</xmax>
			<ymax>983</ymax>
		</bndbox>
	</object>
	<object>
		<name>wall</name>
		<pose>Unspecified</pose>
		<truncated>0</truncated>
		<difficult>0</difficult>
		<bndbox>
			<xmin>649</xmin>
			<ymin>1225</ymin>
			<xmax>672</xmax>
			<ymax>1446</ymax>
		</bndbox>
	</object>
	<object>
		<name>door</name>
		<pose>Unspecified</pose>
		<truncated>0</truncated>
		<difficult>0</difficult>
		<bndbox>
			<xmin>271</xmin>
			<ymin>603</ymin>
			<xmax>325</xmax>
			<ymax>651</ymax>
		</bndbox>
	</object>
	<object>
		<name>door</name>
		<pose>Unspecified</pose>
		<truncated>0</truncated>
		<difficult>0</difficult>
		<bndbox>
			<xmin>342</xmin>
			<ymin>605</ymin>
			<xmax>399</xmax>
			<ymax>659</ymax>
		</bndbox>
	</object>
	<object>
		<name>door</name>
		<pose>Unspecified</pose>
		<truncated>0</truncated>
		<difficult>0</difficult>
		<bndbox>
			<xmin>620</xmin>
			<ymin>1079</ymin>
			<xmax>677</xmax>
			<ymax>1133</ymax>
		</bndbox>
	</object>
	<object>
		<name>door</name>
		<pose>Unspecified</pose>
		<truncated>0</truncated>
		<difficult>0</difficult>
		<bndbox>
			<xmin>620</xmin>
			<ymin>1165</ymin>
			<xmax>677</xmax>
			<ymax>1219</ymax>
		</bndbox>
	</object>
	<object>
		<name>door</name>
		<pose>Unspecified</pose>
		<truncated>0</truncated>
		<difficult>0</difficult>
		<bndbox>
			<xmin>741</xmin>
			<ymin>1051</ymin>
			<xmax>798</xmax>
			<ymax>1105</ymax>
		</bndbox>
	</object>
	<object>
		<name>window</name>
		<pose>Unspecified</pose>
		<truncated>0</truncated>
		<difficult>0</difficult>
		<bndbox>
			<xmin>962</xmin>
			<ymin>822</ymin>
			<xmax>993</xmax>
			<ymax>1030</ymax>
		</bndbox>
	</object>
</annotation>
