<annotation>
	<folder>anatomy</folder>
	<filename>ty01.jpg-im25.jpg</filename>
	<path>C:\Users\MURUGAS\Desktop\implant annotation\anatomy\ty01.jpg-im25.jpg</path>
	<source>
		<database>Unknown</database>
	</source>
	<size>
		<width>443</width>
		<height>723</height>
		<depth>1</depth>
	</size>
	<segmented>0</segmented>
	<object>
		<name>Shoulder - Anotomyhead - Stryker</name>
		<pose>Unspecified</pose>
		<truncated>0</truncated>
		<difficult>0</difficult>
		<bndbox>
			<xmin>72</xmin>
			<ymin>116</ymin>
			<xmax>235</xmax>
			<ymax>312</ymax>
		</bndbox>
	</object>
	<object>
		<name>Shoulder - Anotomytail - Stryker</name>
		<pose>Unspecified</pose>
		<truncated>0</truncated>
		<difficult>0</difficult>
		<bndbox>
			<xmin>133</xmin>
			<ymin>156</ymin>
			<xmax>315</xmax>
			<ymax>448</ymax>
		</bndbox>
	</object>
</annotation>
