<annotation>
	<folder>anatomy</folder>
	<filename>ty01.jpg-im5.jpg</filename>
	<path>C:\Users\MURUGAS\Desktop\implant annotation\anatomy\ty01.jpg-im5.jpg</path>
	<source>
		<database>Unknown</database>
	</source>
	<size>
		<width>443</width>
		<height>723</height>
		<depth>1</depth>
	</size>
	<segmented>0</segmented>
	<object>
		<name>Shoulder - Anotomyhead - Stryker</name>
		<pose>Unspecified</pose>
		<truncated>0</truncated>
		<difficult>0</difficult>
		<bndbox>
			<xmin>276</xmin>
			<ymin>107</ymin>
			<xmax>437</xmax>
			<ymax>327</ymax>
		</bndbox>
	</object>
	<object>
		<name>Shoulder - Anotomytail - Stryker</name>
		<pose>Unspecified</pose>
		<truncated>1</truncated>
		<difficult>0</difficult>
		<bndbox>
			<xmin>326</xmin>
			<ymin>162</ymin>
			<xmax>443</xmax>
			<ymax>418</ymax>
		</bndbox>
	</object>
</annotation>
